pytest_parametrize_cases/__init__.py
pytest_parametrize_cases/case.py
pytest_parametrize_cases/py.typed
pytest_parametrize_cases-0.1.2.dist-info/LICENSE
pytest_parametrize_cases-0.1.2.dist-info/WHEEL
pytest_parametrize_cases-0.1.2.dist-info/METADATA
pytest_parametrize_cases-0.1.2.dist-info/RECORD
