Metadata-Version: 2.1
Name: pytest-parametrize-cases
Version: 0.1.2
Summary: A more user-friendly way to write parametrized tests.
Author: Cameron Pinnegar
Author-email: cameron.pinnegar@gmail.com
Requires-Python: >=3.8,<4.0
Classifier: Programming Language :: Python :: 3
Classifier: Programming Language :: Python :: 3.10
Classifier: Programming Language :: Python :: 3.8
Classifier: Programming Language :: Python :: 3.9
Requires-Dist: pytest (>=6.1.2)
